dsycklehello.py
dsycklehello-0.1.dist-info/METADATA
dsycklehello-0.1.dist-info/WHEEL
dsycklehello-0.1.dist-info/top_level.txt
dsycklehello-0.1.dist-info/RECORD
