Metadata-Version: 2.1
Name: dsycklehello
Version: 0.1
Summary: Say Hello!
Home-page: UNKNOWN
Author: UNKNOWN
Author-email: UNKNOWN
License: UNKNOWN
Platform: UNKNOWN
